.gitignore
.readthedocs.yml
.travis.yml
CHANGELOG.rst
LICENSE
MANIFEST.in
README.rst
setup.cfg
setup.py
tox.ini
docs/Makefile
docs/conf.py
docs/index.rst
docs/installation.rst
docs/_static/custom.css
docs/_static/favicon.ico
docs/_static/logo.png
docs/_static/logo_packed.png
docs/_templates/about.html
docs/api/index.rst
docs/usage/standalone.rst
docs/usage/tendril.rst
src/tendril/__init__.py
src/tendril/apiserver/__init__.py
src/tendril/apiserver/routers/__init__.py
src/tendril/apiserver/routers/interests.py
src/tendril/apiserver/templates/__init__.py
src/tendril/apiserver/templates/base.py
src/tendril/apiserver/templates/interests.py
src/tendril/apiserver/templates/interests_approvals.py
src/tendril/apiserver/templates/interests_graphs.py
src/tendril/apiserver/templates/interests_monitors.py
src/tendril/apiserver/templates/interests_policies.py
src/tendril/authz/__init__.py
src/tendril/authz/approvals/__init__.py
src/tendril/authz/approvals/interests.py
src/tendril/authz/approvals/manager.py
src/tendril/authz/roles/__init__.py
src/tendril/authz/roles/interests.py
src/tendril/authz/roles/interests_approvals.py
src/tendril/authz/roles/interests_policies.py
src/tendril/authz/scopes/__init__.py
src/tendril/authz/scopes/interests.py
src/tendril/common/__init__.py
src/tendril/common/states.py
src/tendril/common/interests/__init__.py
src/tendril/common/interests/approvals.py
src/tendril/common/interests/exceptions.py
src/tendril/common/interests/memberships.py
src/tendril/common/interests/representations.py
src/tendril/config/__init__.py
src/tendril/config/interests.py
src/tendril/core/__init__.py
src/tendril/core/topology/__init__.py
src/tendril/core/topology/monitors.py
src/tendril/db/__init__.py
src/tendril/db/controllers/__init__.py
src/tendril/db/controllers/interests.py
src/tendril/db/controllers/interests_approvals.py
src/tendril/db/controllers/interests_policies.py
src/tendril/db/mixins/__init__.py
src/tendril/db/mixins/interests.py
src/tendril_interests.egg-info/PKG-INFO
src/tendril_interests.egg-info/SOURCES.txt
src/tendril_interests.egg-info/dependency_links.txt
src/tendril_interests.egg-info/requires.txt
src/tendril_interests.egg-info/top_level.txt
